{
  "generator-jhipster": {
    "skipServer": true,
    "databaseType": "sql",
    "devDatabaseType": "sql",
    "prodDatabaseType": "sql",
    "authenticationType": "jwt",
    "blueprints": [],
    "otherModules": [],
    "applicationType": "monolith",
    "baseName": "projectnunsys",
    "jhipsterVersion": "7.0.1",
    "skipClient": false,
    "skipUserManagement": false,
    "skipCheckLengthOfIdentifier": false,
    "skipFakeData": false,
    "jhiPrefix": "jhi",
    "entitySuffix": "",
    "dtoSuffix": "DTO",
    "testFrameworks": [],
    "pages": [],
    "creationTimestamp": 1619538811350,
    "clientFramework": "angularX",
    "withAdminUi": true,
    "clientTheme": "cyborg",
    "clientThemeVariant": "dark",
    "enableTranslation": false,
    "nativeLanguage": "es",
    "clientPackageManager": "npm",
    "packageName": "com.mycompany.myapp",
    "cacheProvider": "ehcache",
    "websocket": false,
    "searchEngine": false,
    "buildTool": "maven",
    "serverPort": "8080",
    "serviceDiscoveryType": false,
    "enableHibernateCache": true,
    "reactive": false,
    "languages": ["en", "fr"],
    "entities": ["Producto", "TipoProducto", "Carrito", "Usuario", "Factura", "Compra"],
    "lastLiquibaseTimestamp": 1619540523000
  }
}
